thesiqtdata.py
thesiqtdata-2.0.0.dist-info/METADATA
thesiqtdata-2.0.0.dist-info/WHEEL
thesiqtdata-2.0.0.dist-info/top_level.txt
thesiqtdata-2.0.0.dist-info/RECORD
