Metadata-Version: 2.1
Name: thesiqtdata
Version: 2.0.0
Summary: my simple package
Home-page: UNKNOWN
Author: Cai The Si
Author-email: caithesi21041997@gmail.com
License: UNKNOWN
Platform: UNKNOWN
